odoo/addons/shopinvader_multi_cart/README.rst
odoo/addons/shopinvader_multi_cart/__init__.py
odoo/addons/shopinvader_multi_cart/__manifest__.py
odoo/addons/shopinvader_multi_cart/i18n/shopinvader_multi_cart.pot
odoo/addons/shopinvader_multi_cart/models/__init__.py
odoo/addons/shopinvader_multi_cart/models/sale_order.py
odoo/addons/shopinvader_multi_cart/readme/CONTRIBUTORS.rst
odoo/addons/shopinvader_multi_cart/readme/DESCRIPTION.rst
odoo/addons/shopinvader_multi_cart/services/__init__.py
odoo/addons/shopinvader_multi_cart/services/cart.py
odoo/addons/shopinvader_multi_cart/services/carts.py
odoo/addons/shopinvader_multi_cart/static/description/index.html
odoo/addons/shopinvader_multi_cart/tests/__init__.py
odoo/addons/shopinvader_multi_cart/tests/test_carts.py
odoo/addons/shopinvader_multi_cart/views/sale_order.xml
odoo14_addon_shopinvader_multi_cart-14.0.1.1.1.dist-info/METADATA
odoo14_addon_shopinvader_multi_cart-14.0.1.1.1.dist-info/WHEEL
odoo14_addon_shopinvader_multi_cart-14.0.1.1.1.dist-info/top_level.txt
odoo14_addon_shopinvader_multi_cart-14.0.1.1.1.dist-info/RECORD
